{
  "ACTOR.TypeCharacter": "Персонаж гравця",
  "ACTOR.TypeNpc": "Персонаж Майстра",
  "ACTOR.TypeVehicle": "Транспорт",
  "ITEM.TypeBackpack": "Рюкзак",
  "ITEM.TypeClass": "Клас",
  "ITEM.TypeConsumable": "Витратне",
  "ITEM.TypeEquipment": "Спорядження",
  "ITEM.TypeFeat": "Риса",
  "ITEM.TypeLoot": "Здобич",
  "ITEM.TypeSpell": "Закляття",
  "ITEM.TypeTool": "Інструмент",
  "ITEM.TypeWeapon": "Зброя",

  "DND5E.title": "D&D 5-та редакція",
  "DND5E.AbbreviationCR": "РВ",
  "DND5E.AbbreviationConc": "Конц.",
  "DND5E.AbbreviationDC": "КС",
  "DND5E.AbbreviationKgs": "кг",
  "DND5E.AbbreviationLR": "ДВ",
  "DND5E.AbbreviationLevel": "Рів.",
  "DND5E.AbbreviationLbs": "фунт.",
  "DND5E.AbbreviationSR": "КВ",
  "DND5E.Ability": "Здібності",
  "DND5E.AbilityStr": "Сила",
  "DND5E.AbilityStrAbbr": "Сил",
  "DND5E.AbilityCon": "Статура",
  "DND5E.AbilityConAbbr": "Ста",
  "DND5E.AbilityDex": "Спритніть",
  "DND5E.AbilityDexAbbr": "Спр",
  "DND5E.AbilityInt": "Інтелект",
  "DND5E.AbilityIntAbbr": "Інт",
  "DND5E.AbilityWis": "Мудрість",
  "DND5E.AbilityWisAbbr": "Мдр",
  "DND5E.AbilityCha": "Харизма",
  "DND5E.AbilityChaAbbr": "Хар",
  "DND5E.AbilityModifier": "Модифікатор здібності",
  "DND5E.AbilityPromptText": "Виберіть тип перевірки {ability}",
  "DND5E.AbilityPromptTitle": "Перевірка {ability}",
  "DND5E.AbilityUseHint": "Налаштуйте використання {name} {type}.",
  "DND5E.AbilityUseUnavailableHint": "У предмета не залишилося зарядів!",
  "DND5E.AbilityUseChargedHint": "{type} заряджено і готово до використання!",
  "DND5E.AbilityUseRechargeHint": "{type} витрачено та вимагає перезарядки!",
  "DND5E.AbilityUseNormalHint": "{type} має {value} з {max} зарядів із залишку {per}.",
  "DND5E.AbilityUseConsumableChargeHint": "Використання {type} витратить 1 заряд із залишку {value}.",
  "DND5E.AbilityUseConsumableQuantityHint": "Використання {type} витратить 1 кількість із залишку {quantity}.",
  "DND5E.AbilityUseConsumableDestroyHint": "Використання {type} витратить останній заряд, і предмет буде видалений.",
  "DND5E.AbilityUseConsume": "Витратити використання здібності?",
  "DND5E.AbilityUseChargesLabel": "{value} зарядів",
  "DND5E.AbilityUseConsumableLabel": "{max} за {per}",
  "DND5E.AbilityUseCast": "Промовити закляття",
  "DND5E.AbilityUseUse": "Вик. здібність",
  "DND5E.AbilityUseConfig": "Налаштування використання",
  "DND5E.Action": "Дія",
  "DND5E.ActionPl": "Дії",
  "DND5E.ActionAbil": "Перевірка здібності",
  "DND5E.ActionHeal": "Лікування",
  "DND5E.ActionMSAK": "Атака закляттям ближнього бою",
  "DND5E.ActionMWAK": "Атака зброєю ближнього бою",
  "DND5E.ActionOther": "Інше",
  "DND5E.ActionRSAK": "Дист. атака закляттям",
  "DND5E.ActionRWAK": "Дист. атака зброєю",
  "DND5E.ActionSave": "Рятунок",
  "DND5E.ActionUtil": "Допоміжне",
  "DND5E.ActionWarningNoItem": "Предмет {item} відсутній у {name}",
  "DND5E.ActionWarningNoToken": "Ви повинні контролювати один або кілька значків, щоб це зробити.",
  "DND5E.ActorWarningInvalidItem": "{itemType} не може бути додано до {actorType}.",
  "DND5E.Add": "Дод.",
  "DND5E.AddEmbeddedItemPromptHint": "Чи бажаєте ви додати ці предмети до листа персонажа?",
  "DND5E.SelectItemsPromptTitle": "Виберіть предмети",
  "DND5E.Advantage": "Перевага",
  "DND5E.Alignment": "Світогляд",
  "DND5E.AlignmentCE": "Хаотично зла", 
  "DND5E.AlignmentCG": "Хаотично добра",
  "DND5E.AlignmentCN": "Хаотично нейтральна",
  "DND5E.AlignmentLE": "Законно зла", 
  "DND5E.AlignmentLG": "Законно добра",
  "DND5E.AlignmentLN": "Законно нейтральна",
  "DND5E.AlignmentNE": "Нейтрально зла",
  "DND5E.AlignmentNG": "Нейтрально добра",
  "DND5E.AlignmentTN": "Нейтральна",
  "DND5E.Appearance": "Зовнішність",
  "DND5E.Apply": "Застосувати",
  "DND5E.Attunement": "Налаштованість",
  "DND5E.AttunementNone": "Налаштованість не потрібна",
  "DND5E.AttunementRequired": "Потрібна налаштованість",
  "DND5E.AttunementAttuned": "Налаштовано",
  "DND5E.Attuned": "Налаштовано", 
  "DND5E.ArmorClass": "Клас броні",
  "DND5E.ArmorClassDefault": "Надіта броня",
  "DND5E.ArmorClassMage": "Магічна броня", 
  "DND5E.ArmorClassDraconic": "Драконяча стійкість",
  "DND5E.ArmorClassUnarmoredMonk": "Захист без броні (монах)",
  "DND5E.ArmorClassUnarmoredBarbarian": "Захист без броні (варвар)",
  "DND5E.ArmorClassCustom": "Своя формула",
  "DND5E.ArmorConfig": "Налаштування броні",
  "DND5E.ArmorConfigHint": "Заповніть поле вище для перезапису автоматичного розрахунку КБ",
  "DND5E.ArmorClassCalculation": "Розрахунок",
  "DND5E.ArmorClassFormula": "Формула",
  "DND5E.AC": "КБ",
  "DND5E.Attack": "Атака",
  "DND5E.AttackPl": "Атаки",
  "DND5E.AttackRoll": "Кидок атаки",
  "DND5E.Attributes": "Показники",
  "DND5E.Background": "Походження",
  "DND5E.Biography": "Біографія",
  "DND5E.Bonds": "Зв'язки",
  "DND5E.BonusAbilityCheck": "Глобальний бонус здібностей",
  "DND5E.BonusAbilitySave": "Глобальний бонус до порятунку",
  "DND5E.BonusAbilitySkill": "Глобальний бонус навичок",
  "DND5E.BonusAction": "Бонусна дія",
  "DND5E.BonusMSAttack": "Мод. атаки закляттям ближнього бою",
  "DND5E.BonusMSDamage": "Мод. пошкодження закляттям ближнього бою",
  "DND5E.BonusMWAttack": "Мод. атаки ближнього бою",
  "DND5E.BonusMWDamage": "Мод. пошкодження ближнього бою",
  "DND5E.BonusRSAttack": "Мод. дист. атаки закляття",
  "DND5E.BonusRSDamage": "Мод. дист. пошкодження закляття",
  "DND5E.BonusRWAttack": "Мод. дист. атаки",
  "DND5E.BonusRWDamage": "Мод. дист. пошкодження",
  "DND5E.BonusSaveForm": "Оновити модифікатори",
  "DND5E.BonusSpellDC": "Глобальний бонус КС заклинань",
  "DND5E.BonusTitle": "Налаштування бонусів персонажа",
  "DND5E.Bonuses": "Глобальний бонус",
  "DND5E.BonusesHint": "Додайте глобальний бонус у вигляді формули, що застосовується до деяких перевірок. Наприклад: 1d4 + 2",
  "DND5E.BonusesInstructions": "Налаштуйте бонуси персонажа, що додаються до певних перевірок.",
  "DND5E.ChallengeRating": "Рівень випробування", 
  "DND5E.Charged": "Заряджено",
  "DND5E.Charges": "Заряди",
  "DND5E.ChatContextDamage": "Завдати пошкодження",
  "DND5E.ChatContextHealing": "Зцілити",
  "DND5E.ChatContextDoubleDamage": "Завдати подвійного пошкодження",
  "DND5E.ChatContextHalfDamage": "Завдати половину пошкодження",
  "DND5E.ChatFlavor": "Додатковий текст в чаті",
  "DND5E.ClassLevels": "Рівні класу",
  "DND5E.ClassMakeOriginal": "Оригінальний клас",
  "DND5E.ClassMakeOriginalHint": "Перший клас, взятий персонажем, що використовується для деяких особливостей мультікласування.",
  "DND5E.ClassName": "Клас",
  "DND5E.ClassOriginal": "Оригінальний клас",
  "DND5E.ClassSaves": "Порятунок",
  "DND5E.ClassSkillsNumber": "Число початкових навичок",
  "DND5E.ClassSkillsEligible": "Доступні навички класу",
  "DND5E.ClassSkillsChosen": "Обрані навички класу",
  "DND5E.ComponentMaterial": "Матеріальний",
  "DND5E.ComponentSomatic": "Жестовий",
  "DND5E.ComponentVerbal": "Словесний",
  "DND5E.ConBlinded": "Сліпота",
  "DND5E.ConCharmed": "Привороження",
  "DND5E.ConDeafened": "Глухота",
  "DND5E.ConDiseased": "Хвороба",
  "DND5E.ConExhaustion": "Виснаження",
  "DND5E.ConFrightened": "Переляк",
  "DND5E.ConGrappled": "Схоплено",
  "DND5E.ConImm": "Імунітет до стану",
  "DND5E.ConIncapacitated": "Знедіяність",
  "DND5E.ConInvisible": "Невидимість",
  "DND5E.ConParalyzed": "Параліч",
  "DND5E.ConPetrified": "Скам'яніння",
  "DND5E.ConPoisoned": "Отруєння",
  "DND5E.ConProne": "Ниць",
  "DND5E.ConRestrained": "Скованість",
  "DND5E.ConStunned": "Приголомшлення",
  "DND5E.ConUnconscious": "Безтямність",
  "DND5E.Concentration": "Концентрація",
  "DND5E.ConsumeTitle": "Витрата ресурсів",
  "DND5E.ConsumeAmmunition": "Боєприпаси",
  "DND5E.ConsumeAttribute": "Ресурси",
  "DND5E.ConsumeMaterial": "Матеріали",
  "DND5E.ConsumeCharges": "Заряди предмета",
  "DND5E.ConsumeWarningNoResource": "{name} витрачає {type}, але ресурс не обрано!",
  "DND5E.ConsumeWarningNoSource": "{type} витрачаються {name}, що більше не існують!",
  "DND5E.ConsumeWarningNoQuantity": "У {name} закінчилися {type}!",
  "DND5E.ConsumeWarningZeroAttribute": "{name} більше не має відповідних ресурсів!",
  "DND5E.ConsumeResource": "Використати ресурс?",
  "DND5E.ConsumeRecharge": "Використати перезарядку?",
  "DND5E.ConsumableAmmunition": "Боєприпас",
  "DND5E.ConsumableFood": "Їжа",
  "DND5E.ConsumablePoison": "Отрута",
  "DND5E.ConsumablePotion": "Зілля",
  "DND5E.ConsumableRod": "Жезл",
  "DND5E.ConsumableScroll": "Сувій",
  "DND5E.ConsumableTrinket": "Дрібничка",
  "DND5E.ConsumableWand": "Паличка",
  "DND5E.ConsumableUseWarnStart": "Це витратне має",
  "DND5E.ConsumableUseWarnEnd": "поточних одиниць",
  "DND5E.ConsumableUnitWarn": "одиниць залишилося",
  "DND5E.ConsumableLastChargeWarn": "Це останній заряд поточної одиниці, та його використання зменшить кількість предметів на 1",
  "DND5E.ConsumableWithoutCharges": "доступно одиниць для використання",
  "DND5E.Consumed": "Витрачено",
  "DND5E.Cover": "Укриття",
  "DND5E.CoverHalf": "Наполовину",
  "DND5E.CoverThreeQuarters": "На три чверті",
  "DND5E.CoverTotal": "Повне",
  "DND5E.CostGP": "Ціна (зм)",
  "DND5E.CreatureAberration": "Аберація",
  "DND5E.CreatureAberrationPl": "Аберація",
  "DND5E.CreatureBeast": "Звір",
  "DND5E.CreatureBeastPl": "Звірі",
  "DND5E.CreatureCelestial": "Небожитель",
  "DND5E.CreatureCelestialPl": "Небожителі",
  "DND5E.CreatureConstruct": "Конструкція",
  "DND5E.CreatureConstructPl": "Конструкції",
  "DND5E.CreatureDragon": "Дракон",
  "DND5E.CreatureDragonPl": "Дракони",
  "DND5E.CreatureElemental": "Елементаль",
  "DND5E.CreatureElementalPl": "Елементалі",
  "DND5E.CreatureFey": "Фея",
  "DND5E.CreatureFeyPl": "Феї",
  "DND5E.CreatureFiend": "Нечисть",
  "DND5E.CreatureFiendPl": "Нечисть",
  "DND5E.CreatureGiant": "Велетень",
  "DND5E.CreatureGiantPl": "Велетні",
  "DND5E.CreatureHumanoid": "Гуманоїд",
  "DND5E.CreatureHumanoidPl": "Гуманоїди",
  "DND5E.CreatureMonstrosity": "Страховисько",
  "DND5E.CreatureMonstrosityPl": "Страховиська",
  "DND5E.CreatureOoze": "Слиз",
  "DND5E.CreatureOozePl": "Слизи",
  "DND5E.CreaturePlant": "Рослина",
  "DND5E.CreaturePlantPl": "Рослини",
  "DND5E.CreatureType": "Тип істоти",
  "DND5E.CreatureTypeTitle": "Налаштування типу істоти",
  "DND5E.CreatureSwarm": "Зграя",
  "DND5E.CreatureSwarmSize": "Розмір зграї",
  "DND5E.CreatureSwarmPhrase": "Зграя з {size} {type}",
  "DND5E.CreatureTypeConfig": "Налаштування типу істоти",
  "DND5E.CreatureTypeSelectorCustom": "Особливий тип",
  "DND5E.CreatureTypeSelectorSubtype": "Підтип",
  "DND5E.CreatureUndead": "Невмерлість",
  "DND5E.CreatureUndeadPl": "Невмерлі",
  "DND5E.Crewed": "З екіпажем",
  "DND5E.Critical": "Критичний",
  "DND5E.CriticalHit": "Критичний удар",
  "DND5E.PowerfulCritical": "Посилений критичний",
  "DND5E.Currency": "Валюта",
  "DND5E.CurrencyCP": "Мідь",
  "DND5E.CurrencyConvert": "Конвертувати монети",
  "DND5E.CurrencyConvertHint": "Дія конвертує всі монети в найвищу валюту, дозволяючи знизити вагу носіння. Відкотити дію не можна.",
  "DND5E.CurrencyEP": "Електрум",
  "DND5E.CurrencyGP": "Золото",
  "DND5E.CurrencyPP": "Платина",
  "DND5E.CurrencySP": "Срібло",
  "DND5E.DamImm": "Імунітет до пошкоджень",
  "DND5E.DamRes": "Опір до пошкоджень",
  "DND5E.DamVuln": "Вразливість до пошкоджень",
  "DND5E.Damage": "Ушкодження",
  "DND5E.DamageAcid": "Кислотне",
  "DND5E.DamageBludgeoning": "Дробильне",
  "DND5E.DamageCold": "Холодне",
  "DND5E.DamageFire": "Вогняне",
  "DND5E.DamageForce": "Силове",
  "DND5E.DamageLightning": "Блискавкою",
  "DND5E.DamageNecrotic": "Некротичне",
  "DND5E.DamagePiercing": "Колюче",
  "DND5E.DamagePhysical": "Фізичне",
  "DND5E.DamagePoison": "Отруйне",
  "DND5E.DamagePsychic": "Психічне",
  "DND5E.DamageRadiant": "Випромінюванням",
  "DND5E.DamageRoll": "Кидок на пошкодження",
  "DND5E.DamageSlashing": "Різальне",
  "DND5E.DamageThunder": "Громове",
  "DND5E.Day": "День",
  "DND5E.DeathSave": "Порятунок від смерті",
  "DND5E.DeathSaveCriticalSuccess": "{name} критично досяг успіху в порятунку від смерті та відновив 1 ОЗ!",
  "DND5E.DeathSaveSuccess": "{name} виживає з 3 успішними порятунками від смерті!",
  "DND5E.DeathSaveFailure": "{name} гине з 3 проваленими порятунками від смерті!",
  "DND5E.DeathSavingThrow": "Кидок порятунку від смерті",
  "DND5E.DeathSaveUnnecessary": "Вам не потрібно проходити порятунками від смерті, тому що у вас більше 0 ОЗ або вже 3 успіхи.",
  "DND5E.Default": "За замовчуванням",
  "DND5E.DefaultAbilityCheck": "Звичайна перевірка",
  "DND5E.Description": "Опис",
  "DND5E.Details": "Подробиці",
  "DND5E.Dimensions": "Розміри",
  "DND5E.Disadvantage": "Завада",
  "DND5E.DistAny": "Будь-яка",
  "DND5E.DistFt": "футів",
  "DND5E.DistKm": "Кілометри",
  "DND5E.DistM": "Метри",
  "DND5E.DistMi": "миль",
  "DND5E.DistSelf": "На себе",
  "DND5E.DistTouch": "Дотик",
  "DND5E.Duration": "Тривалість",
  "DND5E.Effects": "Ефекти",
  "DND5E.EquipmentBonus": "Магічний бонус",
  "DND5E.EquipmentClothing": "Одяг",
  "DND5E.EquipmentHeavy": "Важка броня",
  "DND5E.EquipmentLight": "Легка броня",
  "DND5E.EquipmentMedium": "Середня броня",
  "DND5E.EquipmentNatural": "Природна броня",
  "DND5E.EquipmentShield": "Щит",
  "DND5E.EquipmentShieldProficiency": "Щити",
  "DND5E.EquipmentTrinket": "Дрібничка",
  "DND5E.EquipmentVehicle": "Спорядження транспорту",
  "DND5E.Equipped": "Надягнено",
  "DND5E.Exhaustion": "Виснаженість",
  "DND5E.Expertise": "Уміння",
  "DND5E.FeatureActionRecharge": "Перезарядка",
  "DND5E.Flaws": "Вади",
  "DND5E.EffectCreate": "Створити ефект",
  "DND5E.EffectToggle": "Увімкнути ефект",
  "DND5E.EffectEdit": "Змінити ефект",
  "DND5E.EffectDelete": "Видалити ефект",
  "DND5E.EffectTemporary": "Тимчасові ефекти",
  "DND5E.EffectPassive": "Пасивні ефекти",
  "DND5E.EffectInactive": "Неактивні ефекти",
  "DND5E.EffectNew": "Новий ефект",
  "DND5E.EffectUnavailable": "Недоступні ефекти",
  "DND5E.EffectUnavailableInfo": "Предмет з ефектом повинен бути надітий або налаштований для активації",
  "DND5E.ItemRarityCommon": "звичайний",
  "DND5E.ItemRarityUncommon": "незвичайний",
  "DND5E.ItemRarityRare": "рідкісний",
  "DND5E.ItemRarityVeryRare": "дуже рідкісний",
  "DND5E.ItemRarityLegendary": "легендарний",
  "DND5E.ItemRarityArtifact": "артефакт",
  "DND5E.ItemTypeClass": "Клас",
  "DND5E.ItemTypeClassPl": "Рівні класу",
  "DND5E.ItemTypeConsumable": "Витратне",
  "DND5E.ItemTypeConsumablePl": "Витратні",
  "DND5E.ItemTypeContainer": "Контейнер",
  "DND5E.ItemTypeBackpack": "Рюкзак",
  "DND5E.ItemTypeContainerPl": "Контейнери",
  "DND5E.ItemTypeEquipment": "Спорядження",
  "DND5E.ItemTypeEquipmentPl": "Спорядження",
  "DND5E.ItemTypeFeat": "Риса",
  "DND5E.ItemTypeLoot": "Здобич",
  "DND5E.ItemTypeLootPl": "Здобич",
  "DND5E.ItemTypeTool": "Інструмент",
  "DND5E.ItemTypeToolPl": "Інструменти",
  "DND5E.ItemTypeSpell": "Закляття",
  "DND5E.ItemTypeSpellPl": "Закляття",
  "DND5E.ItemTypeWeapon": "Зброя",
  "DND5E.ItemTypeWeaponPl": "Зброя",
  "DND5E.ItemNoUses": "У {name} не залишилося зарядів.",
  "DND5E.FeatureActive": "Активні особливості",
  "DND5E.FeatureAdd": "Створити особливість",
  "DND5E.FeatureAttack": "Атака особливістю",
  "DND5E.FeaturePassive": "Пасивні особливості",
  "DND5E.FeatureRechargeOn": "Перез. при", 
  "DND5E.FeatureRechargeResult": "Результат 1d6",
  "DND5E.FeatureUsage": "Використання особливостей",
  "DND5E.Features": "Особливості",
  "DND5E.Feats": "Риси",
  "DND5E.FeetAbbr": "фут.",
  "DND5E.Filter": "Фільтр",
  "DND5E.FilterNoSpells": "Закляття з цим фільтром не знайдені.",
  "DND5E.NoSpellLevels": "У цього персонажа немає рівнів заклинателя, але ви можете додати закляття самі.",
  "DND5E.FlagsInstructions": "Налаштуйте вміння та властивості, які впливають на персонажа.",
  "DND5E.FlagsSave": "Оновити вміння",
  "DND5E.FlagsTitle": "Налаштування вміння",
  "DND5E.FlagsDiamondSoul": "Стійкий",
  "DND5E.FlagsDiamondSoulHint": "Уміння у всіх випробуваннях.",
  "DND5E.FlagsPowerfulBuild": "Могутня статура",
  "DND5E.FlagsPowerfulBuildHint": "Додаткова вага для носіння.",
  "DND5E.FlagsElvenAccuracy": "Ельфійська точність",
  "DND5E.FlagsElvenAccuracyHint": "Додатковий кубик при перевірках ЛВК, ІНТ, МДР і ХАР з перевагою.",
  "DND5E.FlagsHalflingLucky": "Удача половинчика",
  "DND5E.FlagsHalflingLuckyHint": "Одне перекидання при перевірках d20.",
  "DND5E.FlagsInitiativeAdv": "Перевага ініціативи",
  "DND5E.FlagsInitiativeAdvHint": "Перевірки ініціативи отримують перевагу.",
  "DND5E.FlagsAlert": "Пильний",
  "DND5E.FlagsAlertHint": "+5 до Ініціативи.",
  "DND5E.FlagsJOAT": "Майстер на всі руки",
  "DND5E.FlagsJOATHint": "Половина бонусу майстерності у навичках, у яких у вас немає майстерності.",
  "DND5E.FlagsObservant": "Уважний",
  "DND5E.FlagsObservantHint": "+5 до пасивного уваги і Розслідування.",
  "DND5E.FlagsReliableTalent": "Надійний",
  "DND5E.FlagsReliableTalentHint": "Вміння класу пройдисвіта.",
  "DND5E.FlagsRemarkableAthlete": "Атлетичний",
  "DND5E.FlagsRemarkableAthleteHint": "Половина бонусу майстерності у перевірках фізичних характеристик та ініціативи.",
  "DND5E.FlagsWeaponCritThreshold": "Поріг крит. атаки зброєю",
  "DND5E.FlagsWeaponCritThresholdHint": "Розширений поріг, при якому відбувається критична атака зброєю.",
  "DND5E.FlagsSpellCritThreshold": "Поріг крит. атаки закляттям",
  "DND5E.FlagsSpellCritThresholdHint": "Розширений поріг, при якому відбувається критична атака закляттям.",
  "DND5E.FlagsMeleeCriticalDice": "Кубики крит. пошкодження",
  "DND5E.FlagsMeleeCriticalDiceHint": "Число додаткових кубиків пошкодження, що додаються до критичних потрапляннь у ближньому бою.",
  "DND5E.Flat": "Незмінний",
  "DND5E.Formula": "(формула)",
  "DND5E.GrantedAbilities": "Отримані здібності",
  "DND5E.HalfProficient": "Напівмайстерний",
  "DND5E.Healing": "Зцілення",
  "DND5E.HealingTemp": "Зцілення (тимчасове)",
  "DND5E.HitPoints": "Од. здоров'я",
  "DND5E.HP": "ОЗ",
  "DND5E.HealthConditions": "Стан здоров'я",
  "DND5E.HPFormula": "Формула здоров'я",
  "DND5E.HitDice": "Кубики здоров'я",
  "DND5E.HitDiceConfig": "Налаштування кубиків здоров'я",
  "DND5E.HitDiceConfigHint": "Налаштуйте залишок кубиків здоров'я для кожного класу",
  "DND5E.HitDiceMax": "Максимальна кількість кубиків здоров'я",
  "DND5E.HitDiceRemaining": "Невикористані кубити здоров'я",
  "DND5E.HitDiceRoll": "Кидок кубиків здоров'я",
  "DND5E.HitDiceUsed": "Використано КЗ",
  "DND5E.HitDiceWarn": "У {name} не залишилося {formula} кубиків здоров'я!",
  "DND5E.Ideals": "Ідеали",
  "DND5E.Identified": "Розпізнано",
  "DND5E.Initiative": "Ініціатива",
  "DND5E.Inspiration": "Натхнення",
  "DND5E.Inventory": "Інвентар",
  "DND5E.ItemActionType": "Тип дії",
  "DND5E.ItemActivationCondition": "Умова активації",
  "DND5E.ItemActivationCost": "Ціна активації",
  "DND5E.ItemAttackBonus": "Модифікатор атаки",
  "DND5E.ItemConsumableActivation": "Витрачає активацію",
  "DND5E.ItemConsumableUsage": "Витрачання",
  "DND5E.ItemConsumableDetails": "Подробиці витратних",
  "DND5E.ItemConsumableStatus": "Статус витратних",
  "DND5E.ItemConsumableType": "Тип витратних",
  "DND5E.ItemContainerCapacity": "Місткість",
  "DND5E.ItemContainerCapacityItems": "Предмети",
  "DND5E.ItemContainerCapacityType": "Тип місткості",
  "DND5E.ItemContainerCapacityWeight": "Вага",
  "DND5E.ItemContainerDetails": "Подробиці контейнера",
  "DND5E.ItemContainerProperties": "Властивості контейнера",
  "DND5E.ItemContainerWeightless": "Вміст без ваги",
  "DND5E.ItemCreate": "Створити предмет",
  "DND5E.ItemDelete": "Видалити предмет",
  "DND5E.ItemDestroyEmpty": "Видалити після витрачання",
  "DND5E.ItemEdit": "Змінити предмет",
  "DND5E.ItemEquipmentAction": "Дія спорядження",
  "DND5E.ItemEquipmentDetails": "Подробиці спорядження",
  "DND5E.ItemEquipmentDexMod": "Макс. мод. спритності",
  "DND5E.ItemEquipmentStatus": "Статус спорядження",
  "DND5E.ItemEquipmentStealthDisav": "Завада скритності",
  "DND5E.ItemEquipmentType": "Тип спорядження",
  "DND5E.ItemEquipmentUsage": "Використання спорядження",
  "DND5E.ItemName": "Назва",
  "DND5E.ItemNew": "Новий {type}",
  "DND5E.ItemRechargeCheck": "{name} перевіряє перезарядку",
  "DND5E.ItemRechargeFailure": "провал!",
  "DND5E.ItemRechargeSuccess": "успіх!",
  "DND5E.ItemRequiredStr": "Необхідна сила",
  "DND5E.ItemToolProficiency": "Майстерність з інструментом",
  "DND5E.ItemToolType": "Тип інструмента",
  "DND5E.ItemWeaponAttack": "Атака зброєю",
  "DND5E.ItemWeaponDetails": "Подробиці атаки",
  "DND5E.ItemWeaponProperties": "Властивості зброї",
  "DND5E.ItemWeaponStatus": "Статус зброї",
  "DND5E.ItemWeaponType": "Тип зброї",
  "DND5E.ItemWeaponUsage": "Використання зброї",
  "DND5E.JackOfAllTrades": "Майстер на всі руки",
  "DND5E.LairAct": "Дії лігва",
  "DND5E.LairActionLabel": "Дія лігва",
  "DND5E.Languages": "Мови",
  "DND5E.LanguagesAarakocra": "Ааракокра",
  "DND5E.LanguagesAbyssal": "Бездонна",
  "DND5E.LanguagesAquan": "Водяна",
  "DND5E.LanguagesAuran": "Аура",
  "DND5E.LanguagesCelestial": "Небесна",
  "DND5E.LanguagesCommon": "Загальна",
  "DND5E.LanguagesDeepSpeech": "Глибинна",
  "DND5E.LanguagesDraconic": "Драконяча",
  "DND5E.LanguagesDruidic": "Друїдська",
  "DND5E.LanguagesDwarvish": "Дворфська",
  "DND5E.LanguagesElvish": "Ельфська",
  "DND5E.LanguagesGiant": "Гігантів",
  "DND5E.LanguagesGith": "Гітска",
  "DND5E.LanguagesGnoll": "Гнолльска",
  "DND5E.LanguagesGnomish": "Гномска",
  "DND5E.LanguagesGoblin": "Гоблінська",
  "DND5E.LanguagesHalfling": "Половинчикова",
  "DND5E.LanguagesIgnan": "Ігнанська",
  "DND5E.LanguagesInfernal": "Пекельна",
  "DND5E.LanguagesOrc": "Орська",
  "DND5E.LanguagesPrimordial": "Одвічна",
  "DND5E.LanguagesSylvan": "Сильвська",
  "DND5E.LanguagesTerran": "Терранська",
  "DND5E.LanguagesThievesCant": "Злодійський жаргон",
  "DND5E.LanguagesUndercommon": "Підзагальна", 
  "DND5E.LegAct": "Легендарні дії",
  "DND5E.LegendaryActionLabel": "Легендарна дія",
  "DND5E.LegRes": "Легендарний опір",
  "DND5E.Level": "Рівень",
  "DND5E.LevelScaling": "Підвищення рівня",
  "DND5E.LimitedUses": "Ліміт використань",
  "DND5E.LongRest": "Довгий відпочинок",
  "DND5E.LongRestNormal": "Довгий відпочинок (8 годин)",
  "DND5E.LongRestGritty": "Довгий відпочинок (7 днів)",
  "DND5E.LongRestEpic": "Довгий відпочинок (1 година)", 
  "DND5E.LongRestOvernight": "Довгий відпочинок (новий день)",
  "DND5E.LongRestHint": "Здійснити довгий відпочинок? У кінці довгого відпочинку персонаж відновлює всі витрачені очки здоров'я, а також половину від максимуму кубиків здоров'я, заряди предметів зі щоденними зарядами й комірки заклять.",
  "DND5E.LongRestResult": "{name} здійснює довгий відпочинок, відновлюючи {health} очок здоров'я і {dice} кубиків здоров'я.",
  "DND5E.LongRestResultHitDice": "{name} здійснює довгий відпочинок і відновлює {dice} кубиків здоров'я.",
  "DND5E.LongRestResultHitPoints": "{name} здійснює довгий відпочинок і відновлює {health} очок здоров'я.",
  "DND5E.LongRestResultShort": "{name} здійснює довгий відпочинок.",
  "DND5E.Max": "Макс.",
  "DND5E.Modifier": "Мод.",
  "DND5E.Name": "Ім'я персонажа",
  "DND5E.NoCharges": "Нема зарядів",
  "DND5E.None": "Жоден", 
  "DND5E.Normal": "Звичайний",
  "DND5E.NotProficient": "Без майстерності",
  "DND5E.OtherFormula": "Інша формула",
  "DND5E.PactMagic": "Договірна магія",
  "DND5E.Passive": "Пасивна",
  "DND5E.PersonalityTraits": "Властивості особистості",
  "DND5E.PlaceTemplate": "Розмістити шаблон",
  "DND5E.Polymorph": "Поліморф",
  "DND5E.PolymorphAcceptSettings": "Особливі налаштування",
  "DND5E.PolymorphKeepBio": "Залишити  біографію",
  "DND5E.PolymorphKeepClass": "Залишити бонус вміння",
  "DND5E.PolymorphKeepFeats": "Залишити особливості",
  "DND5E.PolymorphKeepItems": "Залишити предмети",
  "DND5E.PolymorphKeepMental": "Залишити ІНТ, МДР, ХАР",
  "DND5E.PolymorphKeepPhysical": "Залишити СИЛ, СПР, ВИТ",
  "DND5E.PolymorphKeepSaves": "Залишити рятівні кидки",
  "DND5E.PolymorphKeepSkills": "Залишити вміння в навичках",
  "DND5E.PolymorphKeepSpells": "Залишити закляття",
  "DND5E.PolymorphKeepVision": "Залишити зір (персонажа і значка)",
  "DND5E.PolymorphMergeSaves": "Об'єднати вміння в порятуках (залишити вищий)",
  "DND5E.PolymorphMergeSkills": "Об'єднати вміння в навичках (залишити вищий)",
  "DND5E.PolymorphPromptTitle": "Трансформація дійової особи",
  "DND5E.PolymorphRestoreTransformation": "Відкотити трансформацію",
  "DND5E.PolymorphRevertWarn": "У вас немає прав на скасування поліморфа цієї істоти.",
  "DND5E.PolymorphTmpClass": "Тимчасовий клас",
  "DND5E.PolymorphTokens": "Трансформувати все пов'язані значки?",
  "DND5E.PolymorphWarn": "У вас немає прав на поліморф цієї істоти.",
  "DND5E.PolymorphWildShape": "Дика форма",
  "DND5E.Prepared": "Підгот.",
  "DND5E.Price": "Ціна",
  "DND5E.Proficiency": "Бонус майстерності",
  "DND5E.Proficient": "Майстерний",
  "DND5E.PropertyBase": "Базовий",
  "DND5E.PropertyTotal": "Всього",
  "DND5E.Quantity": "Кількість",
  "DND5E.Race": "Раса",
  "DND5E.RacialTraits": "Расові властивості",
  "DND5E.Range": "Дистанція",
  "DND5E.Rarity": "Рідкісність",
  "DND5E.Reaction": "Реакція",
  "DND5E.ReactionPl": "Реакції",
  "DND5E.Recharge": "Перезарядка",
  "DND5E.RequiredMaterials": "Необхідні матеріали",
  "DND5E.Requirements": "Вимоги",
  "DND5E.ResourcePrimary": "Ресурс 1",
  "DND5E.ResourceSecondary": "Ресурс 2",
  "DND5E.ResourceTertiary": "Ресурс 3",
  "DND5E.Rest": "Відпочинок",
  "DND5E.RestL": "Довг.",
  "DND5E.RestS": "Кор.",
  "DND5E.Ritual": "Ритуал",
  "DND5E.Roll": "Кидок",
  "DND5E.RollExample": "напр. + 1d4",
  "DND5E.RollMode": "Режим кидка",
  "DND5E.RollSituationalBonus": "Ситуаційний бонус?",
  "DND5E.Movement": "Пересування",
  "DND5E.MovementConfig": "Налаштування швидкості пересування",
  "DND5E.MovementConfigHint": "Налаштування швидкості пересування і особливих видів пересування істоти.",
  "DND5E.MovementWalk": "Ходьба",
  "DND5E.MovementBurrow": "Копання",
  "DND5E.MovementClimb": "Лазання",
  "DND5E.MovementHover": "Ширяння",
  "DND5E.MovementFly": "Політ",
  "DND5E.MovementSwim": "Плавання",
  "DND5E.MovementUnits": "Одиниці виміру",
  "DND5E.NewDay": "Новий день?",
  "DND5E.NewDayHint": "Відновити здібності з обмеженням \" в день \"?",
  "DND5E.Senses": "Особливе чуття",
  "DND5E.SensesConfig": "Налаштування чуття",
  "DND5E.SensesConfigHint": "Налаштування особливих видів чуття, якими володіє істота.",
  "DND5E.SenseDarkvision": "Нічний зір",
  "DND5E.SenseBlindsight": "Сліпий зір",
  "DND5E.SenseTremorsense": "Чуття вібрації",
  "DND5E.SenseTruesight": "Істинний зір",
  "DND5E.SenseSpecial": "Особливе чуття",
  "DND5E.SheetClassCharacter": "Стандартний бланк персонажа 5e",
  "DND5E.SheetClassNPC": "Стандартний бланк ПМ 5e",
  "DND5E.SheetClassVehicle": "Стандартний бланк транспорту 5e",
  "DND5E.SheetClassItem": "Стандартний бланк предмета 5e",
  "DND5E.SavingThrow": "Випробування",
  "DND5E.SaveDC": "СК {dc} {ability}",
  "DND5E.SavePromptTitle": "Випробування {ability}",
  "DND5E.ScalingFormula": "Формула підвищення рівня",
  "DND5E.SchoolAbj": "Обмеження",
  "DND5E.SchoolCon": "Втілення",
  "DND5E.SchoolDiv": "Віщування",
  "DND5E.SchoolEnc": "Привороження", 
  "DND5E.SchoolEvo": "Прикликування", 
  "DND5E.SchoolIll": "Ілюзії",
  "DND5E.SchoolNec": "Некромантії",
  "DND5E.SchoolTrs": "Перетворення",
  "DND5E.ShortRest": "Короткий відпочинок",
  "DND5E.ShortRestNormal": "Короткий відпочинок (1 година)",
  "DND5E.ShortRestGritty": "Короткий відпочинок (8 годин)",
  "DND5E.ShortRestEpic": "Короткий відпочинок (5 хвилин)",
  "DND5E.ShortRestOvernight": "Короткий відпочинок (новий день)",
  "DND5E.ShortRestHint": "Здійснити короткий відпочинок? При короткому відпочинку ви можете використовувати кубити здоров'я для зцілення та відновити деякі ресурси.",
  "DND5E.ShortRestNoHD": "Нічого не було КЗ",
  "DND5E.ShortRestResult": "{name} здійснює короткий відпочинок, витрачаючи {dice} кубиків Здоров'я та відновлюючи {health} очок здоров'я.",
  "DND5E.ShortRestResultShort": "{name} здійснює короткий відпочинок.",
  "DND5E.ShortRestSelect": "Виберіть кубик здоров'я",
  "DND5E.Size": "Розмір",
  "DND5E.SizeGargantuan": "Велетенський",
  "DND5E.SizeHuge": "Величезний",
  "DND5E.SizeLarge": "Великий",
  "DND5E.SizeMedium": "Середній",
  "DND5E.SizeSmall": "Маленький",
  "DND5E.SizeTiny": "Крихітний",
  "DND5E.SkillAcr": "Акробатика",
  "DND5E.SkillAni": "Догляд тварин",
  "DND5E.SkillArc": "Аркана", 
  "DND5E.SkillAth": "Атлетика",
  "DND5E.SkillDec": "Обман",
  "DND5E.SkillHis": "Історія",
  "DND5E.SkillIns": "Проникливість",
  "DND5E.SkillInv": "Розслідування",
  "DND5E.SkillItm": "Залякування",
  "DND5E.SkillMed": "Медицина",
  "DND5E.SkillNat": "Природа",
  "DND5E.SkillPer": "Переконливість",
  "DND5E.SkillPrc": "Уважність",
  "DND5E.SkillPrf": "Виконання",
  "DND5E.SkillRel": "Релігія",
  "DND5E.SkillSlt": "Спритність рук",
  "DND5E.SkillSte": "Скритність",
  "DND5E.SkillSur": "Виживання",
  "DND5E.SkillPromptTitle": "Перевірка навички {skill}",
  "DND5E.Skip": "Пропустити",
  "DND5E.Source": "Джерело",
  "DND5E.Special": "Особливе",
  "DND5E.SpecialTraits": "Особливі властивості",
  "DND5E.Speed": "Швидкість",
  "DND5E.SpeedSpecial": "Особлива швидкість",
  "DND5E.SpellAbility": "Закл. Хар-ка", 
  "DND5E.SpellAdd": "Дод.",
  "DND5E.SpellCantrip": "Витівка", 
  "DND5E.SpellCastConsume": "Використитати комірку закляття?",
  "DND5E.SpellCastNoSlots": "У вас недостатньо комірок для накладання закляття",
  "DND5E.SpellCastUpcast": "створити рівня" ,
  "DND5E.SpellcasterLevel": "Рівень заклинателя",
  "DND5E.SpellCastingHeader": "Накладання закляття",
  "DND5E.Spellcasting": "Закл. Хар-ка",
  "DND5E.SpellComponents": "Компоненти закляття",
  "DND5E.SpellCreate": "Створити закляття",
  "DND5E.SpellDC": "КС закл.",
  "DND5E.SpellDetails": "Подробиці закляття",
  "DND5E.SpellEffects": "Ефекти закляття",
  "DND5E.SpellLevel": "Рівень",
  "DND5E.SpellLevel0": "Витівки",
  "DND5E.SpellLevel1": "1-ий рівень",
  "DND5E.SpellLevel2": "2-ий рівень",
  "DND5E.SpellLevel3": "3-ий рівень",
  "DND5E.SpellLevel4": "4-ий рівень",
  "DND5E.SpellLevel5": "5-ий рівень",
  "DND5E.SpellLevel6": "6-ий рівень",
  "DND5E.SpellLevel7": "7-ий рівень",
  "DND5E.SpellLevel8": "8-ий рівень",
  "DND5E.SpellLevel9": "9-ий рівень",
  "DND5E.SpellLevelSlot": "{level} ({n} комірок)",
  "DND5E.SpellLevelPact": "Комірка договору [Ур {level}] ({n} комірок)",
  "DND5E.SpellMaterials": "Матеріали закляття",
  "DND5E.SpellName": "Назва",
  "DND5E.SpellNone": "Ні",
  "DND5E.SpellPrepAtWill": "За бажанням",
  "DND5E.SpellPrepInnate": "Вроджено",
  "DND5E.SpellPrepPrepared": "Підготовка",
  "DND5E.SpellPrepAlways": "Завжди підготовлено",
  "DND5E.SpellPreparationMode": "Тип підготовки",
  "DND5E.SpellPrepared": "Підготовлено",
  "DND5E.SpellProgArt": "Техномаг",
  "DND5E.SpellProgFull": "Повний заклинатель",
  "DND5E.SpellProgHalf": "Частковий заклинатель",
  "DND5E.SpellProgOverride": "Як перезаписати комірки",
  "DND5E.SpellProgPact": "Договірна магія",
  "DND5E.SpellProgThird": "Третинний заклинатель",
  "DND5E.SpellProgression": "Розвиток закляття",
  "DND5E.SpellSchool": "Школа",
  "DND5E.SpellScroll": "Сувій закляття",
  "DND5E.SpellTarget": "Ціль",
  "DND5E.SpellUnprepared": "Не підготовлено",
  "DND5E.SpellUsage": "Використання",
  "DND5E.Spellbook": "Закляття",
  "DND5E.StealthDisadvantage": "Завада скритності",
  "DND5E.SubclassName": "Підклас",
  "DND5E.Supply": "Припаси",
  "DND5E.Target": "Ціль",
  "DND5E.TargetAlly": "Союзник",
  "DND5E.TargetCone": "Конус",
  "DND5E.TargetCreature": "Істота",
  "DND5E.TargetCube": "Куб",
  "DND5E.TargetCylinder": "Циліндр",
  "DND5E.TargetEnemy": "Ворог",
  "DND5E.TargetLine": "Лінія",
  "DND5E.TargetObject": "Об'єкт",
  "DND5E.TargetRadius": "Радіус",
  "DND5E.TargetSelf": "На себе",
  "DND5E.TargetSpace": "Місце",
  "DND5E.TargetSphere": "Сфера",
  "DND5E.TargetSquare": "Квадрат",
  "DND5E.TargetWall": "Стіна",
  "DND5E.TargetWidth": "Ширина лінії",
  "DND5E.Temp": "Час.",
  "DND5E.Threshold": "Поріг",
  "DND5E.TimeDay": "День",
  "DND5E.TimeHour": "Час",
  "DND5E.TimeInst": "Миттєве",
  "DND5E.TimeMinute": "Хвилина",
  "DND5E.TimeMonth": "Місяць",
  "DND5E.TimePerm": "Постійне",
  "DND5E.TimeRound": "Раунд",
  "DND5E.TimeTurn": "Хід",
  "DND5E.TimeYear": "Рік",
  "DND5E.ToolArtisans": "Інструменти ремесла",
  "DND5E.ToolCheck": "Перевірка інструменту",
  "DND5E.ToolDisguiseKit": "Набір для маскування",
  "DND5E.ToolForgeryKit": "Набір для фальсифікації",
  "DND5E.ToolGamingSet": "Ігровий набір",
  "DND5E.ToolHerbalismKit": "Набір травника",
  "DND5E.ToolMusicalInstrument": "Музичний інструмент",
  "DND5E.ToolNavigators": "Інструменти навігатора",
  "DND5E.ToolPoisonersKit": "Інструменти отруйника",
  "DND5E.ToolThieves": "Інструменти крадія",
  "DND5E.ToolVehicle": "Транспорт",
  "DND5E.TraitArmorProf": "Майстерність з бронею",
  "DND5E.TraitSave": "Оновити",
  "DND5E.TraitSelectorSpecial": "Особливі (розділяй крапкою з комою)",
  "DND5E.TraitToolProf": "Мастерність з інструментом",
  "DND5E.TraitWeaponProf": "Майстерність зі зброєю",
  "DND5E.Type": "Тип",
  "DND5E.Uncrewed": "Без екіпажу",
  "DND5E.Unequipped": "Не надіто",
  "DND5E.Unlimited": "Необмежено",
  "DND5E.Usage": "Використання",
  "DND5E.Use": "Використовувати",
  "DND5E.Uses": "Залишилося",
  "DND5E.Vehicle": "Транспорт",
  "DND5E.VehicleActionStations": "Дія станції",
  "DND5E.VehicleActionThresholds": "Поріг дії транспорту",
  "DND5E.VehicleCargo": "Вантаж",
  "DND5E.VehicleCargoCapacity": "Вантажопідйомність",
  "DND5E.VehicleCargoCrew": "Наповнення",
  "DND5E.VehicleCreatureCapacity": "Макс. місць",
  "DND5E.VehicleCrew": "Екіпаж",
  "DND5E.VehicleCrewed": "З екіпажем",
  "DND5E.VehicleCrewAction": "Дія екіпажу",
  "DND5E.VehicleEquipment": "Спорядження транспорту",
  "DND5E.VehicleMishap": "Поломка",
  "DND5E.VehiclePassengers": "Пасажири",
  "DND5E.VehicleTypeAir": "Повітряний транспорт",
  "DND5E.VehicleTypeLand": "Наземний транспорт",
  "DND5E.VehicleTypeWater": "Водний транспорт",
  "DND5E.VehicleUncrewed": "Без екіпажу",
  "DND5E.Versatile": "Універсальна",
  "DND5E.VersatileDamage": "Покодження з 2 рук",
  "DND5E.VsDC": "зі КС",
  "DND5E.WarnBadACFormula": "Введена формула КБ не може бути розрахована.",
  "DND5E.WarnMultipleArmor": "Надягнено більше одного комплекту броні. Розрахунок КБ може бути некоректним.",
  "DND5E.WarnMultipleShields": "Надягнено більш одного щита. Розрахунок КБ може бути некоректним.",
  "DND5E.WeaponImprov": "Імпровізована",
  "DND5E.WeaponMartialM": "Військова ближнього бою",
  "DND5E.WeaponMartialProficiency": "Військова зброя",
  "DND5E.WeaponMartialR": "Військова дист.",
  "DND5E.WeaponNatural": "Природна",
  "DND5E.WeaponPropertiesAda": "Адамантієва",
  "DND5E.WeaponPropertiesAmm": "Боєприпаси",
  "DND5E.WeaponPropertiesFin": "Фехтув.",
  "DND5E.WeaponPropertiesFir": "Вогнепал",
  "DND5E.WeaponPropertiesFoc": "Фокус",
  "DND5E.WeaponPropertiesHvy": "Важка",
  "DND5E.WeaponPropertiesLgt": "Легка",
  "DND5E.WeaponPropertiesLod": "Арбалет",
  "DND5E.WeaponPropertiesMgc": "Магічна",
  "DND5E.WeaponPropertiesRch": "Довга",
  "DND5E.WeaponPropertiesRel": "Перез.",
  "DND5E.WeaponPropertiesRet": "Вертається",
  "DND5E.WeaponPropertiesSil": "Посріблена",
  "DND5E.WeaponPropertiesSpc": "Особлива",
  "DND5E.WeaponPropertiesThr": "Метальна",
  "DND5E.WeaponPropertiesTwo": "Дворучна",
  "DND5E.WeaponPropertiesVer": "Універс.",
  "DND5E.WeaponSiege": "Зброя для облоги",
  "DND5E.WeaponSimpleM": "Проста ближнього бою",
  "DND5E.WeaponSimpleProficiency": "Проста зброя",
  "DND5E.WeaponSimpleR": "Проста дист.",
  "DND5E.Weight": "Вага",
  "DND5E.available": "доступно",
  "DND5E.description": "Система Dungeons & Dragons 5th Edition в Foundry VTT.",
  "DND5E.of": "з",
  "DND5E.per": "за",
  "DND5E.spell": "закляття",

  "SETTINGS.5eAllowPolymorphingL": "Дозволити гравцям поліморф своїх персонажів.",
  "SETTINGS.5eAllowPolymorphingN": "Дозволити поліморф",
  "SETTINGS.5eAutoCollapseCardL": "Автоматично згортати опис на картках предметів в чаті.",
  "SETTINGS.5eAutoCollapseCardN": "Звертати картки предметів",
  "SETTINGS.5eAutoSpellTemplateL": "При створенні закляття буде автоматично створюватися вимірювальний шаблон (гравець повинен мати роль довіреної)",
  "SETTINGS.5eAutoSpellTemplateN": "Завжди розміщувати шаблон закляття",
  "SETTINGS.5eCurWtL": "Монети впливають на навантаження згідно КГ стор. 143.",
  "SETTINGS.5eCurWtN": "Враховувати вагу",
  "SETTINGS.5eDiagEuclidean": "Евклідова метрика (діагональ 7,07 футів)",
  "SETTINGS.5eDiagL": "Виберіть правила діагонального руху у вашій грі.",
  "SETTINGS.5eDiagN": "Діагональний рух",
  "SETTINGS.5eDiagPHB": "Книга Гравця (5/5/5)",
  "SETTINGS.5eDiagDMG": "Керівництво Майстра (5/10/5)",
  "SETTINGS.5eInitTBL": "Використовувати показник Спритності для вирішення нічиєї при перевірці ініціативи.",
  "SETTINGS.5eInitTBN": "Нічия ініціативи вирішується Спритністю",
  "SETTINGS.5eNoExpL": "Приховати смугу досвіду в листі персонажа.",
  "SETTINGS.5eNoExpN": "Не відстежувати досвід",
  "SETTINGS.5eReset": "Скидання",
  "SETTINGS.5eRestL": "Налаштуйте правила відпочинку у вашій грі.",
  "SETTINGS.5eRestN": "Варіант відпочинку",
  "SETTINGS.5eRestPHB": "Книга Гравця (ДВ: 8 годин, КВ: 1 година)",
  "SETTINGS.5eRestGritty": "Жорстокий реалізм (ДВ: 7 днів, КВ: 8 годин)",
  "SETTINGS.5eRestEpic": "Епічна героїка (ДВ: 1 годину, КВ: 1 хв)",
  "SETTINGS.5eUndoChanges": "Відмовитися від змін",
  "SETTINGS.5eMetricN": "Використовувати метричну систему",
  "SETTINGS.5eMetricL": "Заміна системи мір і ваг на метричну: фунти на кілограми, а фути на метри."
}
